README.md
pyproject.toml
setup.py
laolang.python_demo.egg-info/PKG-INFO
laolang.python_demo.egg-info/SOURCES.txt
laolang.python_demo.egg-info/dependency_links.txt
laolang.python_demo.egg-info/top_level.txt
pj_build/__init__.py
pj_build/exit_code_parser.py
pj_build/replace_version.py
pj_build/text_version.py
pj_deploy/__init__.py
python_demo/__init__.py
python_demo/built_in/__init__.py
python_demo/built_in/attr_examples.py
python_demo/built_in/dict_examples.py
python_demo/built_in/doctest_examples.py
python_demo/built_in/glob_fnmatch_examples.py
python_demo/built_in/math_examples.py
python_demo/built_in/os_examples.py
python_demo/built_in/sequence_unpacking_examples.py
python_demo/built_in/starred_expressions_examples.py
python_demo/built_in/string_examples.py
python_demo/built_in/traceback_examples.py
python_demo/built_in/zip_examples.py
python_demo/flask/__init__.py
python_demo/flask/hello_app.py
python_demo/flask/session_app.py
python_demo/numpy/__init__.py
python_demo/pandas/__init__.py
python_demo/pytest/__init__.py
python_demo/pytest/conftest.py
python_demo/pytest/run_all_cases.py
python_demo/pytest/test_assertions_about_expected_exceptions.py
python_demo/pytest/test_fixtures.py
python_demo/pytest/test_foo_compare.py
python_demo/pytest/test_marks.py
python_demo/pytest/test_parametrize.py
tests/__init__.py
tests/run_all_cases.py
tests/integration/__init__.py
tests/unit/__init__.py
tests/unit/conftest.py
tests/unit/pj_build/__init__.py
tests/unit/pj_build/run_all_pi_build_cases.py
tests/unit/pj_build/test_replace_version.py
tests/unit/python_demo/__init__.py
tests/unit/python_demo/run_all_python_demo_cases.py